jupyterlab_python_file/__init__.py
jupyterlab_python_file/_version.py
jupyterlab_python_file/labextension/build_log.json
jupyterlab_python_file/labextension/package.json
jupyterlab_python_file/labextension/static/lib_index_js.3659277a81b7993d5df0.js
jupyterlab_python_file/labextension/static/lib_index_js.3659277a81b7993d5df0.js.map
jupyterlab_python_file/labextension/static/remoteEntry.f62c832d551cd3d9e2a3.js
jupyterlab_python_file/labextension/static/remoteEntry.f62c832d551cd3d9e2a3.js.map
jupyterlab_python_file/labextension/static/style.js
jupyterlab_python_file/labextension/static/style_index_js.7207f7f8198937efcc9d.js
jupyterlab_python_file/labextension/static/style_index_js.7207f7f8198937efcc9d.js.map
jupyterlab_python_file/labextension/static/vendors-node_modules_css-loader_dist_runtime_api_js-node_modules_css-loader_dist_runtime_cssW-926fd9.7a47723e3f3a8c3e3d80.js
jupyterlab_python_file/labextension/static/vendors-node_modules_css-loader_dist_runtime_api_js-node_modules_css-loader_dist_runtime_cssW-926fd9.7a47723e3f3a8c3e3d80.js.map
jupyterlab_python_file-0.5.5.data/data/share/jupyter/labextensions/jupyterlab-python-file/build_log.json
jupyterlab_python_file-0.5.5.data/data/share/jupyter/labextensions/jupyterlab-python-file/install.json
jupyterlab_python_file-0.5.5.data/data/share/jupyter/labextensions/jupyterlab-python-file/package.json
jupyterlab_python_file-0.5.5.data/data/share/jupyter/labextensions/jupyterlab-python-file/static/lib_index_js.3659277a81b7993d5df0.js
jupyterlab_python_file-0.5.5.data/data/share/jupyter/labextensions/jupyterlab-python-file/static/lib_index_js.3659277a81b7993d5df0.js.map
jupyterlab_python_file-0.5.5.data/data/share/jupyter/labextensions/jupyterlab-python-file/static/remoteEntry.f62c832d551cd3d9e2a3.js
jupyterlab_python_file-0.5.5.data/data/share/jupyter/labextensions/jupyterlab-python-file/static/remoteEntry.f62c832d551cd3d9e2a3.js.map
jupyterlab_python_file-0.5.5.dist-info/LICENSE
jupyterlab_python_file-0.5.5.dist-info/METADATA
jupyterlab_python_file-0.5.5.dist-info/WHEEL
jupyterlab_python_file-0.5.5.dist-info/top_level.txt
jupyterlab_python_file-0.5.5.dist-info/RECORD
